proxyx/__init__.py
proxyx/app.py
proxyx/errors.py
proxyx/logging.yaml
proxyx/models.py
proxyx/py.typed
proxyx/settings.py
proxyx/utils.py
proxyx-0.0.4.dist-info/LICENSE
proxyx-0.0.4.dist-info/WHEEL
proxyx-0.0.4.dist-info/METADATA
proxyx-0.0.4.dist-info/RECORD
